isa_location.py
isa_location-0.1.1.dist-info/METADATA
isa_location-0.1.1.dist-info/WHEEL
isa_location-0.1.1.dist-info/RECORD
