Metadata-Version: 2.1
Name: isa_location
Version: 0.1.1
Summary: well, this is my first poetry project
Author: sasya
Requires-Python: >=3.8.2,<4.0.0
Classifier: Programming Language :: Python :: 3
Classifier: Programming Language :: Python :: 3.9
Classifier: Programming Language :: Python :: 3.10
Classifier: Programming Language :: Python :: 3.11
Classifier: Programming Language :: Python :: 3.12
Requires-Dist: elasticsearch (>=8.13.0,<9.0.0)
Requires-Dist: pip (>=24.0,<25.0)
Requires-Dist: requests (>=2.31.0,<3.0.0)
